README.md
setup.py
malogin/__init__.py
malogin/login.py
malogin.egg-info/PKG-INFO
malogin.egg-info/SOURCES.txt
malogin.egg-info/dependency_links.txt
malogin.egg-info/top_level.txt