Metadata-Version: 2.1
Name: malogin
Version: 0.1.2
Summary: get cookies of malogin
Home-page: https://github.com/yinguohai
Author: bluesky8
Author-email: guohaiyin8@gmail.com
License: UNKNOWN
Platform: UNKNOWN
Classifier: Programming Language :: Python :: 3.7
Classifier: License :: OSI Approved :: MIT License
Classifier: Operating System :: OS Independent
